{
    "key": "group_brooklyn_beauty_our_work",
    "title": "Homepage: Our Work",
    "fields": [
        {
            "key": "field_brooklyn_beauty_our_work_title",
            "label": "Section Title",
            "name": "our_work_title",
            "aria-label": "",
            "type": "text",
            "instructions": "",
            "required": 0,
            "conditional_logic": 0,
            "wrapper": {
                "width": "",
                "class": "",
                "id": ""
            },
            "default_value": "",
            "maxlength": "",
            "allow_in_bindings": 0,
            "placeholder": "",
            "prepend": "",
            "append": ""
        },
        {
            "key": "field_brooklyn_beauty_our_work_text",
            "label": "Section Text",
            "name": "our_work_text",
            "aria-label": "",
            "type": "textarea",
            "instructions": "",
            "required": 0,
            "conditional_logic": 0,
            "wrapper": {
                "width": "",
                "class": "",
                "id": ""
            },
            "default_value": "",
            "maxlength": "",
            "allow_in_bindings": 0,
            "rows": 3,
            "placeholder": "",
            "new_lines": ""
        },
        {
            "key": "field_brooklyn_beauty_our_work_label",
            "label": "Left Label",
            "name": "our_work_label",
            "aria-label": "",
            "type": "text",
            "instructions": "Decorative handwritten label near the gallery.",
            "required": 0,
            "conditional_logic": 0,
            "wrapper": {
                "width": "50",
                "class": "",
                "id": ""
            },
            "default_value": "",
            "maxlength": "",
            "allow_in_bindings": 0,
            "placeholder": "",
            "prepend": "",
            "append": ""
        },
        {
            "key": "field_brooklyn_beauty_our_work_button_text",
            "label": "Button Text",
            "name": "our_work_button_text",
            "aria-label": "",
            "type": "text",
            "instructions": "",
            "required": 0,
            "conditional_logic": 0,
            "wrapper": {
                "width": "25",
                "class": "",
                "id": ""
            },
            "default_value": "",
            "maxlength": "",
            "allow_in_bindings": 0,
            "placeholder": "",
            "prepend": "",
            "append": ""
        },
        {
            "key": "field_brooklyn_beauty_our_work_button_link",
            "label": "Button Link",
            "name": "our_work_button_link",
            "aria-label": "",
            "type": "url",
            "instructions": "",
            "required": 0,
            "conditional_logic": 0,
            "wrapper": {
                "width": "25",
                "class": "",
                "id": ""
            },
            "default_value": "",
            "allow_in_bindings": 0,
            "placeholder": ""
        },
        {
            "key": "field_brooklyn_beauty_our_work_items",
            "label": "Slider Items",
            "name": "our_work_items",
            "aria-label": "",
            "type": "repeater",
            "instructions": "Each slide should include a preview image and a video file.",
            "required": 0,
            "conditional_logic": 0,
            "wrapper": {
                "width": "",
                "class": "",
                "id": ""
            },
            "layout": "row",
            "pagination": 0,
            "min": 0,
            "max": 0,
            "collapsed": "",
            "button_label": "Add Slide",
            "rows_per_page": 20,
            "sub_fields": [
                {
                    "key": "field_brooklyn_beauty_our_work_item_preview_image",
                    "label": "Preview Image",
                    "name": "preview_image",
                    "aria-label": "",
                    "type": "image",
                    "instructions": "",
                    "required": 1,
                    "conditional_logic": 0,
                    "wrapper": {
                        "width": "50",
                        "class": "",
                        "id": ""
                    },
                    "return_format": "id",
                    "library": "all",
                    "min_width": "",
                    "min_height": "",
                    "min_size": "",
                    "max_width": "",
                    "max_height": "",
                    "max_size": "",
                    "mime_types": "",
                    "allow_in_bindings": 0,
                    "preview_size": "medium",
                    "parent_repeater": "field_brooklyn_beauty_our_work_items"
                },
                {
                    "key": "field_brooklyn_beauty_our_work_item_video_file",
                    "label": "Video",
                    "name": "video_file",
                    "aria-label": "",
                    "type": "file",
                    "instructions": "",
                    "required": 0,
                    "conditional_logic": 0,
                    "wrapper": {
                        "width": "50",
                        "class": "",
                        "id": ""
                    },
                    "return_format": "id",
                    "library": "all",
                    "min_size": "",
                    "max_size": "",
                    "mime_types": "mp4,webm,m4v,mov,ogg",
                    "allow_in_bindings": 0,
                    "parent_repeater": "field_brooklyn_beauty_our_work_items"
                }
            ]
        }
    ],
    "location": [
        [
            {
                "param": "page_type",
                "operator": "==",
                "value": "front_page"
            }
        ]
    ],
    "menu_order": 40,
    "position": "normal",
    "style": "default",
    "label_placement": "top",
    "instruction_placement": "label",
    "hide_on_screen": "",
    "active": true,
    "description": "Content settings for the Our Work section on homepage.",
    "show_in_rest": 0,
    "display_title": "",
    "modified": 1771094790
}
